concat_images.py
concat_images-0.2.0.dist-info/licenses/LICENSE
concat_images-0.2.0.dist-info/METADATA
concat_images-0.2.0.dist-info/WHEEL
concat_images-0.2.0.dist-info/entry_points.txt
concat_images-0.2.0.dist-info/top_level.txt
concat_images-0.2.0.dist-info/RECORD
