Metadata-Version: 2.4
Name: concat-images
Version: 0.2.0
Summary: Combine multiple images into one with customizable orientation, spacing, and alignment
Author: Aleš Kancilija
License-Expression: MIT
Project-URL: Homepage, https://github.com/mrpesho/concat-images
Project-URL: Repository, https://github.com/mrpesho/concat-images
Project-URL: Issues, https://github.com/mrpesho/concat-images/issues
Keywords: image,concatenate,combine,pillow,cli
Classifier: Development Status :: 4 - Beta
Classifier: Environment :: Console
Classifier: Intended Audience :: Developers
Classifier: Operating System :: OS Independent
Classifier: Programming Language :: Python :: 3
Classifier: Programming Language :: Python :: 3.8
Classifier: Programming Language :: Python :: 3.9
Classifier: Programming Language :: Python :: 3.10
Classifier: Programming Language :: Python :: 3.11
Classifier: Programming Language :: Python :: 3.12
Classifier: Topic :: Multimedia :: Graphics
Classifier: Typing :: Typed
Requires-Python: >=3.8
License-File: LICENSE
Requires-Dist: Pillow>=10.0.0
Provides-Extra: dev
Requires-Dist: pytest>=7.0.0; extra == "dev"
Dynamic: license-file
